jschemator/__init__.py
jschemator/fields.py
jschemator-0.0.9.dist-info/LICENSE
jschemator-0.0.9.dist-info/METADATA
jschemator-0.0.9.dist-info/WHEEL
jschemator-0.0.9.dist-info/top_level.txt
jschemator-0.0.9.dist-info/RECORD
