Metadata-Version: 2.1
Name: jschemator
Version: 0.0.9
Summary: A class interface for data modeling with json-schema
License-File: LICENSE
Provides-Extra: dev
Requires-Dist: pytest ; extra == 'dev'
Requires-Dist: pytest-cov ; extra == 'dev'
Requires-Dist: pytest-asyncio ; extra == 'dev'
Requires-Dist: aiosow ; extra == 'dev'
